{"stats":{"minecraft:dropped":{"minecraft:wheat_seeds":1,"minecraft:tnt":1,"minecraft:deepslate":1,"minecraft:oak_planks":1,"minecraft:stone_slab":1,"minecraft:grass_block":1,"minecraft:polished_andesite":5,"minecraft:gold_block":1,"minecraft:gray_concrete":1,"minecraft:white_concrete":3,"minecraft:mangrove_stairs":1,"minecraft:glass":1,"minecraft:stone_brick_stairs":1},"minecraft:picked_up":{"minecraft:wheat":2,"minecraft:repeater":1,"minecraft:potato":7,"minecraft:gold_block":1,"minecraft:wheat_seeds":40,"minecraft:bamboo":1,"minecraft:sugar_cane":1,"minecraft:stick":10,"minecraft:sweet_berries":8,"minecraft:grass_block":1,"minecraft:redstone":2,"minecraft:tnt":1,"minecraft:polished_andesite":5,"minecraft:pumpkin_seeds":2,"minecraft:mangrove_stairs":1,"minecraft:glow_berries":4},"minecraft:custom":{"minecraft:leave_game":14,"minecraft:time_since_death":708481,"minecraft:time_since_rest":708481,"minecraft:sprint_one_cm":2017,"minecraft:walk_one_cm":977402,"minecraft:drop":19,"minecraft:fly_one_cm":1391377,"minecraft:open_chest":1,"minecraft:crouch_one_cm":4944,"minecraft:play_time":708481,"minecraft:sneak_time":11612,"minecraft:walk_under_water_one_cm":31029,"minecraft:jump":1047,"minecraft:walk_on_water_one_cm":1292,"minecraft:total_world_time":708481},"minecraft:used":{"minecraft:wheat_seeds":97,"minecraft:oak_fence":55,"minecraft:petrified_oak_slab":94,"minecraft:nether_brick_fence":6,"minecraft:water_bucket":22,"minecraft:dead_bush":12,"minecraft:dark_oak_sign":1,"minecraft:dispenser":2,"minecraft:smooth_quartz_slab":1,"minecraft:red_concrete":2,"minecraft:redstone":28,"minecraft:polished_andesite":2872,"minecraft:red_nether_bricks":1,"minecraft:mangrove_planks":15,"minecraft:ladder":8,"minecraft:oak_sign":15,"minecraft:andesite_slab":38,"minecraft:spruce_planks":117,"minecraft:tinted_glass":1,"minecraft:stone":554,"minecraft:cauldron":3,"minecraft:red_nether_brick_stairs":3,"minecraft:green_bed":2,"minecraft:sugar_cane":4,"minecraft:stone_hoe":147,"minecraft:farmland":7,"minecraft:deepslate_bricks":212,"minecraft:netherrack":1,"minecraft:jungle_wood":2,"minecraft:glow_berries":3,"minecraft:cocoa_beans":1,"minecraft:crafting_table":1,"minecraft:white_carpet":5,"minecraft:tnt":4,"minecraft:hopper":4,"minecraft:red_bed":5,"minecraft:jungle_planks":14,"minecraft:blast_furnace":4,"minecraft:carrot":63,"minecraft:yellow_concrete":1,"minecraft:stone_stairs":126,"minecraft:dark_oak_fence_gate":15,"minecraft:gray_concrete":118,"minecraft:warped_pressure_plate":4,"minecraft:warped_planks":4,"minecraft:smoker":5,"minecraft:pumpkin_seeds":2,"minecraft:oak_fence_gate":10,"minecraft:birch_door":5,"minecraft:redstone_torch":3,"minecraft:andesite_wall":21,"minecraft:glass":358,"minecraft:lever":2,"minecraft:wooden_hoe":103,"minecraft:sea_lantern":2,"minecraft:black_concrete":2,"minecraft:mangrove_log":2,"minecraft:oxeye_daisy":13,"minecraft:bookshelf":32,"minecraft:daylight_detector":818,"minecraft:mangrove_stairs":169,"minecraft:gray_stained_glass_pane":3,"minecraft:heavy_weighted_pressure_plate":52,"minecraft:iron_block":4,"minecraft:grass_block":655,"minecraft:oak_stairs":71,"minecraft:pig_spawn_egg":15,"minecraft:spruce_button":1,"minecraft:polished_andesite_stairs":438,"minecraft:stone_button":11,"minecraft:map":7,"minecraft:jungle_log":2,"minecraft:spruce_pressure_plate":10,"minecraft:stone_slab":514,"minecraft:light_blue_bed":3,"minecraft:spruce_trapdoor":2,"minecraft:iron_door":146,"minecraft:deepslate":3,"minecraft:melon_seeds":2,"minecraft:stone_bricks":220,"minecraft:stone_brick_stairs":73,"minecraft:polished_andesite_slab":74,"minecraft:soul_lantern":14,"minecraft:bamboo":10,"minecraft:green_candle":1,"minecraft:stripped_mangrove_log":342,"minecraft:repeater":8,"minecraft:red_nether_brick_wall":2,"minecraft:brown_carpet":62,"minecraft:scaffolding":15,"minecraft:horn_coral":9,"minecraft:hay_block":171,"minecraft:iron_trapdoor":4,"minecraft:sweet_berries":2,"minecraft:furnace":2,"minecraft:oak_sapling":8,"minecraft:mangrove_slab":28,"minecraft:white_stained_glass_pane":151,"minecraft:jungle_door":29,"minecraft:white_stained_glass":22,"minecraft:beetroot_seeds":1,"minecraft:andesite":21,"minecraft:glass_pane":509,"minecraft:gold_block":39,"minecraft:stone_pressure_plate":4,"minecraft:white_concrete":8300,"minecraft:potato":64,"minecraft:kelp":3,"minecraft:gray_wool":31,"minecraft:dandelion":5,"minecraft:smooth_stone":33,"minecraft:bone_meal":47,"minecraft:large_fern":12,"minecraft:horn_coral_fan":3,"minecraft:stripped_spruce_wood":31,"minecraft:gray_stained_glass":22}},"DataVersion":3218}